{
  "features": {
    "taste": {
      "positive": ["맛있", "존맛", "맛집", "고소", "담백", "깔끔한 맛", "풍미", "신선"],
      "negative": ["맛없", "맛이 없", "짜다", "싱겁", "느끼", "비리", "질기"]
    },
    "value": {
      "positive": ["가성비", "저렴", "합리적", "가격 괜찮", "혜자"],
      "negative": ["비싸", "가격대비 별로", "창렬", "아깝", "가격이 부담"]
    },
    "portion": {
      "positive": ["양 많", "양이 많", "푸짐", "넉넉", "배부", "든든"],
      "negative": ["양 적", "양이 적", "양이 부족", "양이 아쉽"]
    },
    "brightness": {
      "bright": ["밝", "화사", "채광", "환한"],
      "dark": ["어둡", "은은한 조명", "조명이 은은", "간접 조명", "캔들"]
    },
    "noise": {
      "quiet": ["조용", "차분", "대화하기 좋", "잔잔"],
      "lively": ["시끌", "활기", "북적", "왁자", "핫플"]
    },
    "spaciousness": {
      "spacious": ["넓", "쾌적", "자리 많", "테이블 간격"],
      "cozy": ["아늑", "작지만", "오붓", "좁"]
    },
    "seat_type": {
      "couple": ["2인석", "데이트", "창가"],
      "group": ["단체석", "회식", "모임", "테이블 붙"],
      "bar": ["바 자리", "바석", "카운터"],
      "floor": ["좌식"],
      "room": ["룸", "개별룸", "프라이빗"]
    }
  },
  "labels": {
    "couple_meal": ["데이트", "여친", "남친", "기념일", "분위기 좋", "감성", "무드"],
    "couple_drink": ["데이트", "와인", "칵테일", "무드", "바", "분위기 좋"],
    "friend_meal": [
      "친구", "친구랑", "친구들", "동기", "애들", "애들이랑",
      "수다", "편하게", "모임", "같이", "다같이", "여럿이",
      "맛집 탐방", "먹방", "워라밸", "퇴근 후", "가볍게"
    ],
    "friend_drink": [
      "친구", "친구랑", "친구들", "동기",
      "술", "안주", "맥주", "소주", "소맥", "한잔",
      "시끌", "2차", "포차", "치맥", "호프", "맥주집",
      "삼겹살에 소주", "고기에 술"
    ],
    "business_meal": ["회식", "단체", "미팅", "조용", "예약", "룸"],
    "business_drink": ["회식", "단체", "룸", "넓", "안주", "술자리"]
  },
  "negation_prefixes": ["안 ", "못 ", "안해", "못해", "아닌", "없"]
}
